[
  {
    "key": 1,
    "image": "https://assets.pokemon.com/assets/cms2/img/cards/web/XY1/XY1_EN_42.png",
    "category": "Baseball Cards",
    "name": "Verreaux's sifaka",
    "description": "Adaptive 6th generation array",
    "startPrice": 10,
    "myBid": 50,
    "highestBid": 90,
    "buyout": 150,
    "endTime": "2022-03-24 20:30",
    "ownerId": 1,
    "orderStatus": "bidding"
  },
  {
    "key": 2,
    "image": "https://assets.pokemon.com//assets/cms2/img/cards/site_search/CEL/CEL_EN_11.png",
    "category": "Baseball Cards",
    "name": "Boa, malagasy ground",
    "description": "Intuitive well-modulated core",
    "startPrice": 10,
    "myBid": 70,
    "highestBid": 200,
    "buyout": 210,
    "endTime": "2022-03-25 20:30",
    "ownerId": 2,
    "orderStatus": "bidding"
  },
  {
    "key": 3,
    "image": "https://assets.pokemon.com//assets/cms2/img/cards/site_search/SWSH9/SWSH9_EN_147.png",
    "category": "Baseball Cards",
    "name": "Black-backed magpie",
    "description": "Intuitive web-enabled matrix",
    "startPrice": 10,
    "myBid": 100,
    "highestBid": 100,
    "buyout": 167,
    "endTime": "2022-04-25 20:30",
    "ownerId": 1,
    "orderStatus": "bidding"
  },
  {
    "key": 4,
    "image": "https://assets.pokemon.com/assets/cms2/img/cards/web/XY1/XY1_EN_42.png",
    "category": "Baseball Cards",
    "name": "Verreaux's sifaka",
    "description": "Adaptive 6th generation array",
    "startPrice": 10,
    "myBid": 50,
    "highestBid": 90,
    "buyout": 150,
    "endTime": "2022-03-24 20:30",
    "ownerId": 1,
    "orderStatus": "bidding"
  },
  {
    "key": 5,
    "image": "https://assets.pokemon.com//assets/cms2/img/cards/site_search/CEL/CEL_EN_11.png",
    "category": "Baseball Cards",
    "name": "Boa, malagasy ground",
    "description": "Intuitive well-modulated core",
    "startPrice": 10,
    "myBid": 70,
    "highestBid": 200,
    "buyout": 210,
    "endTime": "2022-03-25 20:30",
    "ownerId": 2,
    "orderStatus": "bidding"
  },
  {
    "key": 6,
    "image": "https://assets.pokemon.com//assets/cms2/img/cards/site_search/SWSH9/SWSH9_EN_147.png",
    "category": "Baseball Cards",
    "name": "Black-backed magpie",
    "description": "Intuitive web-enabled matrix",
    "startPrice": 10,
    "myBid": 100,
    "highestBid": 100,
    "buyout": 167,
    "endTime": "2022-04-25 20:30",
    "ownerId": 1,
    "orderStatus": "bidding"
  },
  {
    "key": 7,
    "image": "https://assets.pokemon.com/assets/cms2/img/cards/web/XY1/XY1_EN_42.png",
    "category": "Baseball Cards",
    "name": "Verreaux's sifaka",
    "description": "Adaptive 6th generation array",
    "startPrice": 10,
    "myBid": 50,
    "highestBid": 90,
    "buyout": 150,
    "endTime": "2022-03-24 20:30",
    "ownerId": 1,
    "orderStatus": "bidding"
  },
  {
    "key": 8,
    "image": "https://assets.pokemon.com//assets/cms2/img/cards/site_search/CEL/CEL_EN_11.png",
    "category": "Baseball Cards",
    "name": "Boa, malagasy ground",
    "description": "Intuitive well-modulated core",
    "startPrice": 10,
    "myBid": 70,
    "highestBid": 200,
    "buyout": 210,
    "endTime": "2022-03-25 20:30",
    "ownerId": 2,
    "orderStatus": "bidding"
  },
  {
    "key": 9,
    "image": "https://assets.pokemon.com//assets/cms2/img/cards/site_search/SWSH9/SWSH9_EN_147.png",
    "category": "Baseball Cards",
    "name": "Black-backed magpie",
    "description": "Intuitive web-enabled matrix",
    "startPrice": 10,
    "myBid": 100,
    "highestBid": 100,
    "buyout": 167,
    "endTime": "2022-04-25 20:30",
    "ownerId": 1,
    "orderStatus": "bidding"
  },
  {
    "key": 10,
    "image": "https://assets.pokemon.com/assets/cms2/img/cards/web/XY1/XY1_EN_42.png",
    "category": "Baseball Cards",
    "name": "Verreaux's sifaka",
    "description": "Adaptive 6th generation array",
    "startPrice": 10,
    "myBid": 50,
    "highestBid": 90,
    "buyout": 150,
    "endTime": "2022-03-24 20:30",
    "ownerId": 1,
    "orderStatus": "bidding"
  },
  {
    "key": 12,
    "image": "https://assets.pokemon.com//assets/cms2/img/cards/site_search/CEL/CEL_EN_11.png",
    "category": "Baseball Cards",
    "name": "Boa, malagasy ground",
    "description": "Intuitive well-modulated core",
    "startPrice": 10,
    "myBid": 70,
    "highestBid": 200,
    "buyout": 210,
    "endTime": "2022-03-25 20:30",
    "ownerId": 2,
    "orderStatus": "bidding"
  },
  {
    "key": 13,
    "image": "https://assets.pokemon.com//assets/cms2/img/cards/site_search/SWSH9/SWSH9_EN_147.png",
    "category": "Baseball Cards",
    "name": "Black-backed magpie",
    "description": "Intuitive web-enabled matrix",
    "startPrice": 10,
    "myBid": 100,
    "highestBid": 100,
    "buyout": 167,
    "endTime": "2022-04-25 20:30",
    "ownerId": 1,
    "orderStatus": "bidding"
  },
  {
    "key": 14,
    "image": "https://assets.pokemon.com/assets/cms2/img/cards/web/XY1/XY1_EN_42.png",
    "category": "Baseball Cards",
    "name": "Verreaux's sifaka",
    "description": "Adaptive 6th generation array",
    "startPrice": 10,
    "myBid": 50,
    "highestBid": 90,
    "buyout": 150,
    "endTime": "2022-03-24 20:30",
    "ownerId": 1,
    "orderStatus": "bidding"
  }
]
